DB.py
IFrame.py
JavaScript.py
Timings.py
framewalker-0.5.dist-info/DESCRIPTION.rst
framewalker-0.5.dist-info/METADATA
framewalker-0.5.dist-info/RECORD
framewalker-0.5.dist-info/WHEEL
framewalker-0.5.dist-info/metadata.json
framewalker-0.5.dist-info/top_level.txt
