Metadata-Version: 2.0
Name: framewalker
Version: 0.5
Summary: UNKNOWN
Home-page: https://github.com/stefanbie/FrameWalker
Author: UNKNOWN
Author-email: UNKNOWN
License: UNKNOWN
Platform: UNKNOWN
Requires-Dist: PyMySQL
Requires-Dist: peewee
